autodocx/__init__.py
autodocx/errors/__base.py
autodocx/errors/__init__.py
autodocx/functions/__init__.py
autodocx/functions/__tokens.py
autodocx/scripts/__base.py
autodocx/scripts/__generate.py
autodocx/scripts/__init__.py
autodocx-0.1.0.dist-info/METADATA
autodocx-0.1.0.dist-info/WHEEL
autodocx-0.1.0.dist-info/entry_points.txt
autodocx-0.1.0.dist-info/top_level.txt
autodocx-0.1.0.dist-info/RECORD
