Metadata-Version: 2.1
Name: autodocx
Version: 0.1.0
Summary: A tool for automating Microsoft Word Documents generation
Home-page: https://github.com/juancerezo/python-autodocx
Author: Juan Cerezo
Keywords: docx,word,doc,automation,automated,microsoft,office,document,generator,generation,build,excel
Requires-Python: >=3.10.*
Requires-Dist: click (==8.1.3)
Requires-Dist: python-docx (==0.8.11)
Requires-Dist: openpyxl (==3.0.10)
